nautobot_device_resources/__init__.py
nautobot_device_resources/consts.py
nautobot_device_resources/filters.py
nautobot_device_resources/forms.py
nautobot_device_resources/models.py
nautobot_device_resources/navigation.py
nautobot_device_resources/tables.py
nautobot_device_resources/template_content.py
nautobot_device_resources/urls.py
nautobot_device_resources/views.py
nautobot_device_resources/api/__init__.py
nautobot_device_resources/api/serializers.py
nautobot_device_resources/api/urls.py
nautobot_device_resources/api/views.py
nautobot_device_resources/generic/__init__.py
nautobot_device_resources/generic/forms.py
nautobot_device_resources/generic/views.py
nautobot_device_resources/migrations/0001_initial.py
nautobot_device_resources/migrations/0002_cpu_separate_model.py
nautobot_device_resources/migrations/0003_create_resources.py
nautobot_device_resources/migrations/__init__.py
nautobot_device_resources/templates/nautobot_device_resources/cpu.html
nautobot_device_resources/templates/nautobot_device_resources/cpu_edit.html
nautobot_device_resources/templates/nautobot_device_resources/cpu_manufacturer_extension.html
nautobot_device_resources/templates/nautobot_device_resources/device_resources.html
nautobot_device_resources/templates/nautobot_device_resources/device_resources_edit.html
nautobot_device_resources/tests/__init__.py
nautobot_device_resources/tests/setups.py
nautobot_device_resources/tests/test_forms.py
nautobot_device_resources/tests/test_models.py
nautobot_device_resources/tests/test_template_content.py
nautobot_device_resources/tests/test_views.py
nautobot_device_resources-1.0.0.dist-info/LICENSE
nautobot_device_resources-1.0.0.dist-info/METADATA
nautobot_device_resources-1.0.0.dist-info/WHEEL
nautobot_device_resources-1.0.0.dist-info/top_level.txt
nautobot_device_resources-1.0.0.dist-info/RECORD
