Metadata-Version: 2.1
Name: nautobot-device-resources
Version: 1.0.0
Summary: Nautobot Device Resources plugin
Author-email: Jakub Krysl <jakub.krysl@gmail.com>
Maintainer-email: Jakub Krysl <jakub.krysl@gmail.com>
License: Apache License
Project-URL: homepage, https://github.com/Thetacz/nautobot-plugin-device-resources
Project-URL: repository, https://github.com/Thetacz/nautobot-plugin-device-resources.git
Keywords: nautobot,nautobot-plugin
Classifier: Programming Language :: Python
Requires-Python: >=3.8
License-File: LICENSE
Requires-Dist: nautobot (<=2.0.0,>=1.5.0)
Provides-Extra: dev
Requires-Dist: black ; extra == 'dev'
Requires-Dist: coverage[toml] ; extra == 'dev'
Requires-Dist: factory-boy ; extra == 'dev'
Requires-Dist: mypy ; extra == 'dev'
Requires-Dist: pre-commit ; extra == 'dev'
Requires-Dist: pre-commit-hooks ; extra == 'dev'
Requires-Dist: pylint ; extra == 'dev'
Requires-Dist: pylint-django ; extra == 'dev'
Requires-Dist: pytest ; extra == 'dev'
Requires-Dist: pytest-cov ; extra == 'dev'
Requires-Dist: pytest-mock ; extra == 'dev'
Requires-Dist: pytest-order ; extra == 'dev'
Requires-Dist: types-PyYAML ; extra == 'dev'
